xtracer/__init__.py
xtracer/log.py
xtracer/main.py
xtracer/mbi.py
xtracer/utils.py
xtracer/xic.py
xtracer/xim.py
xtracer/xix.py
xtracer/sdk/__init__.py
xtracer_pamaf-1.3.0.dist-info/METADATA
xtracer_pamaf-1.3.0.dist-info/WHEEL
xtracer_pamaf-1.3.0.dist-info/entry_points.txt
xtracer_pamaf-1.3.0.dist-info/top_level.txt
xtracer_pamaf-1.3.0.dist-info/RECORD
