Metadata-Version: 2.4
Name: xtracer-pamaf
Version: 1.3.0
Summary: Converting PAMAF .mbi data to pseudo-MS/MS files by untargeted methods.
Author-email: Jian Song <jian.song.2025@outlook.com>
License: MIT
Requires-Python: ==3.12.11
Requires-Dist: numpy==1.26.4
Requires-Dist: numba==0.61.2
